hello/__init__.py
hello/temp.py
hello_tst27-0.1.0.dist-info/METADATA
hello_tst27-0.1.0.dist-info/WHEEL
hello_tst27-0.1.0.dist-info/top_level.txt
hello_tst27-0.1.0.dist-info/RECORD
