Metadata-Version: 2.4
Name: hello_tst27
Version: 0.1.0
Summary: Simple hello package
Author: Your Name
Author-email: you@example.com
Requires-Python: >=3.6
